rate_limiter/__init__.py
rate_limiter/common.py
rate_limiter/exceptions.py
rate_limiter/py.typed
rate_limiter_decorator-0.0.8.dist-info/METADATA
rate_limiter_decorator-0.0.8.dist-info/WHEEL
rate_limiter_decorator-0.0.8.dist-info/RECORD
