Metadata-Version: 2.3
Name: rate-limiter-decorator
Version: 0.0.8
Summary: A Python async rate limiter using Redis and Lua with sliding window algorithm. Supports retries, exponential backoff, and optional exception handling.
Author: Вадим Бажов
Author-email: master@remort.net
Requires-Python: >=3.10,<4.0
Classifier: Programming Language :: Python :: 3
Classifier: Programming Language :: Python :: 3.10
Classifier: Programming Language :: Python :: 3.11
Classifier: Programming Language :: Python :: 3.12
Classifier: Programming Language :: Python :: 3.13
Requires-Dist: redis (>=6.4.0,<7.0.0)
